{
  "id": 320239,
  "title": "血与心",
  "city": "中国",
  "cover": "https://image.xinu.ink/pic/data/737/images/320239.jpg",
  "color": "#80402a",
  "modified": 1726916304282,
  "litePoints": [
    {
      "id": "nozyzj4uc",
      "cn": "阜新南站",
      "name": "阜新站",
      "image": "https://image.anitabi.cn/points/320239/nozyzj4uc_1725000097215_cut.jpg?plan=h160",
      "ep": 1,
      "s": 330,
      "geo": [
        41.9851,
        121.6327
      ]
    },
    {
      "id": "np0o4sti4",
      "cn": "人民空军东北老航校旧址",
      "name": "人民空军东北老航校旧址",
      "image": "https://image.anitabi.cn/points/320239/np0o4sti4_1725000102779_cut.jpg?plan=h160",
      "ep": 12,
      "s": 100,
      "geo": [
        44.5418,
        129.5749
      ]
    },
    {
      "id": "npj2vb35n",
      "cn": "辽宁省北镇市六台子村",
      "name": "辽宁省北镇市六台子村",
      "image": "https://image.anitabi.cn/points/320239/npj2vb35n_1726916300443_c16v9.jpg?plan=h160",
      "ep": 4,
      "s": 150,
      "geo": [
        41.523,
        121.9579
      ]
    }
  ],
  "pointsLength": 3,
  "imagesLength": 3,
  "local_id": 737,
  "cn": "血与心：日籍解放军战士砂原惠的传奇人生",
  "region": [
    "海州区",
    "西安区",
    "北镇市"
  ]
}