[
  {
    "id": "nar0af28s",
    "cn": "东京站 18号线站台",
    "name": "東京駅 18番線ホーム",
    "image": "https://image.xinu.ink/pic/data/873/images/nar0af28s_1723871429051.jpg",
    "ep": 1,
    "s": 11,
    "geo": [
      35.6826,
      139.7688
    ],
    "origin": "Anitabi@Lilin",
    "originURL": "https://anitabi.cn/"
  },
  {
    "id": "nar86sdg4",
    "cn": "东京站 18号线站台 4号车厢",
    "name": "東京駅 18番線ホーム 4号車",
    "image": "https://image.xinu.ink/pic/data/873/images/nar86sdg4_1723871836777.jpg",
    "ep": 1,
    "s": 55,
    "geo": [
      35.6817,
      139.7685
    ],
    "origin": "Anitabi@Lilin",
    "originURL": "https://anitabi.cn/"
  },
  {
    "id": "narcyudqn",
    "cn": "东京站 东海道·山阳新干线中央换乘口",
    "name": "東京駅 東海道·山陽新幹線中央のりかえ口",
    "image": "https://image.xinu.ink/pic/data/873/images/narcyudqn_1723872549868.jpg",
    "ep": 1,
    "s": 57,
    "geo": [
      35.6813,
      139.7679
    ],
    "origin": "Anitabi@Lilin",
    "originURL": "https://anitabi.cn/"
  },
  {
    "id": "narpre2f2",
    "cn": "东京站 新干线售票处前",
    "name": "東京駅 新幹線きっぷうりば前",
    "image": "https://image.xinu.ink/pic/data/873/images/narpre2f2_1723872746240.jpg",
    "ep": 1,
    "s": 60,
    "geo": [
      35.6813,
      139.7675
    ],
    "origin": "Anitabi@Lilin",
    "originURL": "https://anitabi.cn/"
  },
  {
    "id": "nas3c5zcc",
    "cn": "东京站 丸之内南口方向指示牌",
    "name": "東京駅 丸の内南口向き案内板",
    "image": "https://image.xinu.ink/pic/data/873/images/nas3c5zcc_1723873603269.jpg",
    "ep": 1,
    "s": 69,
    "geo": [
      35.6803,
      139.7671
    ],
    "origin": "Anitabi@Lilin",
    "originURL": "https://anitabi.cn/"
  },
  {
    "id": "nas8qiszi",
    "cn": "东京站 10号线楼梯下",
    "name": "東京駅 10番線階段下",
    "image": "https://image.xinu.ink/pic/data/873/images/nas8qiszi_1723873894924.jpg",
    "ep": 1,
    "s": 76,
    "geo": [
      35.6804,
      139.767
    ],
    "origin": "Anitabi@Lilin",
    "originURL": "https://anitabi.cn/"
  },
  {
    "id": "nasj823oo",
    "cn": "东京站 9·10号线楼梯下",
    "name": "東京駅 9·10番線階段下",
    "image": "https://image.xinu.ink/pic/data/873/images/nasj823oo_1723874531258.jpg",
    "ep": 1,
    "s": 78,
    "geo": [
      35.6804,
      139.7669
    ],
    "origin": "Anitabi@Lilin",
    "originURL": "https://anitabi.cn/"
  },
  {
    "id": "nasle85rb",
    "cn": "东京站 7·8号线楼梯下",
    "name": "東京駅 7·8番線階段下",
    "image": "https://image.xinu.ink/pic/data/873/images/nasle85rb_1723875143362.jpg",
    "ep": 1,
    "s": 83,
    "geo": [
      35.6804,
      139.7668
    ],
    "origin": "Anitabi@Lilin",
    "originURL": "https://anitabi.cn/"
  },
  {
    "id": "nbc04g5z5",
    "cn": "东京站 千疋屋总店",
    "name": "東京駅 千疋屋総本店",
    "image": "https://image.xinu.ink/pic/data/873/images/nbc04g5z5_1723916904296.jpg",
    "ep": 1,
    "s": 86,
    "geo": [
      35.6804,
      139.7667
    ],
    "origin": "Anitabi@Lilin",
    "originURL": "https://anitabi.cn/"
  },
  {
    "id": "nbc2k3aqx",
    "cn": "东京站 6号线楼梯下",
    "name": "東京駅 6番線階段下",
    "image": "https://image.xinu.ink/pic/data/873/images/nbc2k3aqx_1723917107255.jpg",
    "ep": 1,
    "s": 89,
    "geo": [
      35.6805,
      139.7666
    ],
    "origin": "Anitabi@Lilin",
    "originURL": "https://anitabi.cn/"
  },
  {
    "id": "nbc7gzi6y",
    "cn": "东京站 5·6号线楼梯下",
    "name": "東京駅 5·6番線階段下",
    "image": "https://image.xinu.ink/pic/data/873/images/nbc7gzi6y_1723917359190.jpg",
    "ep": 1,
    "s": 91,
    "geo": [
      35.6805,
      139.7665
    ],
    "origin": "Anitabi@Lilin",
    "originURL": "https://anitabi.cn/"
  },
  {
    "id": "nbca2h2iu",
    "cn": "东京站 丸之内南口检票闸机内",
    "name": "東京駅 丸の内南口改札内",
    "image": "https://image.xinu.ink/pic/data/873/images/nbca2h2iu_1723917508575.jpg",
    "ep": 1,
    "s": 93,
    "geo": [
      35.6804,
      139.766
    ],
    "origin": "Anitabi@Lilin",
    "originURL": "https://anitabi.cn/"
  },
  {
    "id": "nbcdwrlnl",
    "cn": "东京站 丸之内南口穹顶",
    "name": "東京駅 丸の内南口ドーム",
    "image": "https://image.xinu.ink/pic/data/873/images/nbcdwrlnl_1723917811823.jpg",
    "ep": 1,
    "s": 99,
    "geo": [
      35.6805,
      139.7657
    ],
    "origin": "Anitabi@Lilin",
    "originURL": "https://anitabi.cn/"
  },
  {
    "id": "nbcg8uxi6",
    "cn": "东京站 丸之内南口绿窗口前",
    "name": "東京駅 丸の内南口みどりの窓口前",
    "image": "https://image.xinu.ink/pic/data/873/images/nbcg8uxi6_1723917891606.jpg",
    "ep": 1,
    "s": 101,
    "geo": [
      35.6805,
      139.7658
    ],
    "origin": "Anitabi@Lilin",
    "originURL": "https://anitabi.cn/"
  },
  {
    "id": "nbckgcibx",
    "cn": "东京站 丸之内北口指示牌",
    "name": "東京駅 丸の内北口案内板",
    "image": "https://image.xinu.ink/pic/data/873/images/nbckgcibx_1723918219702.jpg",
    "ep": 1,
    "s": 109,
    "geo": [
      35.6822,
      139.7661
    ],
    "origin": "Anitabi@Lilin",
    "originURL": "https://anitabi.cn/"
  },
  {
    "id": "nato9t3yl",
    "name": "丸の内南口圆形大厅",
    "image": "https://image.xinu.ink/pic/data/873/images/nato9t3yl_1723877020890.jpg",
    "ep": 1,
    "s": 103,
    "geo": [
      35.6805,
      139.7657
    ],
    "origin": "Anitabi@月即别",
    "originURL": "https://anitabi.cn/"
  },
  {
    "id": "koce1sfwr",
    "name": "川崎駅前東",
    "image": "https://image.xinu.ink/pic/data/873/images/koce1sfwr-1716473211351.jpg",
    "ep": "OP",
    "s": 160,
    "geo": [
      35.5311,
      139.6993
    ],
    "originLink": "https://maps.app.goo.gl/6q8ZJ597mTQG8c5V7"
  },
  {
    "id": "n4k3o9td2",
    "name": "川崎モアーズ",
    "image": "https://image.xinu.ink/pic/data/873/images/n4k3o9td2-1723386008346.jpg",
    "ep": "OP",
    "s": 163,
    "geo": [
      35.5303,
      139.7
    ],
    "origin": "Anitabi@Lilin",
    "originURL": "https://anitabi.cn/"
  },
  {
    "id": "n94be4ej3",
    "cn": "CLUB CITTA'",
    "name": "川崎クラブチッタ",
    "image": "https://image.xinu.ink/pic/data/873/images/n94be4ej3_1723743439837.jpg",
    "ep": "OP",
    "s": 165,
    "geo": [
      35.5277,
      139.6971
    ],
    "origin": "@kobaya",
    "originLink": "https://www.google.com/maps/d/u/0/edit?mid=1MHZGV3AafVleHD6pVEo5qp_sUZYI9l8&usp=sharing"
  },
  {
    "id": "n6dwafuxy",
    "name": "河原町団地15号棟",
    "image": "https://image.xinu.ink/pic/data/873/images/n6dwafuxy_1723529499844.jpg",
    "ep": "OP",
    "s": 168,
    "geo": [
      35.5388,
      139.692
    ],
    "origin": "Anitabi@Lilin",
    "originURL": "https://anitabi.cn/"
  },
  {
    "id": "n4kweof8e",
    "name": "大島4丁目歩道橋",
    "image": "https://image.xinu.ink/pic/data/873/images/n4kweof8e-1723387754858.jpg",
    "ep": "OP",
    "s": 170,
    "geo": [
      35.5251,
      139.7133
    ],
    "origin": "Anitabi@Lilin",
    "originURL": "https://anitabi.cn/"
  },
  {
    "id": "jfyvtm4n4",
    "name": "幸区都町歩道橋",
    "image": "https://image.xinu.ink/pic/data/873/images/jfyvtm4n4-1723389338438.jpg",
    "ep": "OP",
    "s": 172,
    "geo": [
      35.5359,
      139.6875
    ],
    "origin": "Anitabi@Lilin",
    "originURL": "https://anitabi.cn/"
  },
  {
    "id": "n4ig52q7v",
    "cn": "Brillia e-Square 十字路口",
    "name": "ブリリアイースクエア 交差点",
    "image": "https://image.xinu.ink/pic/data/873/images/n4ig52q7v-1723382426777.jpg",
    "ep": "OP",
    "s": 184,
    "geo": [
      35.5401,
      139.6862
    ],
    "origin": "Anitabi@Lilin",
    "originURL": "https://anitabi.cn/"
  },
  {
    "id": "n4lkt21z7",
    "cn": "天飞隧道",
    "name": "天飛トンネル",
    "image": "https://image.xinu.ink/pic/data/873/images/n4lkt21z7-1723389228202.jpg",
    "ep": "OP",
    "s": 186,
    "geo": [
      35.5174,
      139.7013
    ],
    "origin": "Anitabi@Lilin",
    "originURL": "https://anitabi.cn/"
  },
  {
    "id": "jy4qn2xm7",
    "cn": "カラオケ ビッグエコー川崎東口駅前店",
    "name": "训练用的BigEcho",
    "image": "https://image.xinu.ink/pic/data/873/images/jy4qn2xm7_1723528662123.jpg",
    "ep": "OP",
    "s": 193,
    "geo": [
      35.5309,
      139.6995
    ],
    "origin": "@世界第一托尔厨",
    "originLink": "https://maps.app.goo.gl/tWxGcqbi45zL1QT2A"
  },
  {
    "id": "n93usu86t",
    "cn": "SoundStudio八泉 楼梯",
    "name": "サウンドスタジオ八泉 階段",
    "image": "https://image.xinu.ink/pic/data/873/images/n93usu86t_1723742438997.jpg",
    "ep": "OP",
    "s": 202,
    "geo": [
      35.5281,
      139.6998
    ],
    "origin": "@kobaya",
    "originLink": "https://www.google.com/maps/d/u/0/edit?mid=1MHZGV3AafVleHD6pVEo5qp_sUZYI9l8&usp=sharing"
  },
  {
    "id": "jy4mw9531",
    "name": "川崎站前东口公路",
    "image": "https://image.xinu.ink/pic/data/873/images/jy4mw9531-1714419317839.jpg",
    "ep": "OP",
    "s": 226,
    "geo": [
      35.5311,
      139.6994
    ],
    "origin": "@世界第一托尔厨",
    "originLink": "https://www.google.com/maps/d/edit?mid=1eNSBc8cHUr-G6NHNahY9hyjez4vmdHo&usp=sharing"
  },
  {
    "id": "nd3r0ad5d",
    "name": "熊本駅 白川口(東口)駅前広場",
    "image": "https://image.xinu.ink/pic/data/873/images/nd3r0ad5d_1724055715916.jpg",
    "ep": "OP",
    "s": 226,
    "geo": [
      32.7898,
      130.6896
    ],
    "origin": "Anitabi@Lilin",
    "originURL": "https://anitabi.cn/"
  },
  {
    "id": "n6eore4xe",
    "name": "川崎駅前",
    "image": "https://image.xinu.ink/pic/data/873/images/n6eore4xe_1723530956111.jpg",
    "ep": 1,
    "s": 235,
    "geo": [
      35.5301,
      139.6975
    ],
    "origin": "Anitabi@月即别",
    "originURL": "https://anitabi.cn/"
  },
  {
    "id": "pd9n4fv08",
    "name": "アパマンショップ川崎北口店",
    "image": "https://image.xinu.ink/pic/data/873/images/pd9n4fv08_1729710713986.jpg",
    "ep": 1,
    "s": 236,
    "geo": [
      35.5318,
      139.6988
    ],
    "origin": "Anitabi@Lilin",
    "originURL": "https://anitabi.cn/"
  },
  {
    "id": "n6jkfkveo",
    "name": "南河原公園",
    "image": "https://image.xinu.ink/pic/data/873/images/n6jkfkveo_1723541590052.jpg",
    "ep": 1,
    "s": 253,
    "geo": [
      35.536,
      139.6887
    ],
    "origin": "Anitabi@Lilin",
    "originURL": "https://anitabi.cn/"
  },
  {
    "id": "n6jq0vdce",
    "name": "南河原公園 入口信号",
    "image": "https://image.xinu.ink/pic/data/873/images/n6jq0vdce_1723541943511.jpg",
    "ep": 1,
    "s": 257,
    "geo": [
      35.5371,
      139.6883
    ],
    "origin": "Anitabi@Lilin",
    "originURL": "https://anitabi.cn/"
  },
  {
    "id": "n6jwzwc93",
    "name": "さいわい緑道 横断歩道",
    "image": "https://image.xinu.ink/pic/data/873/images/n6jwzwc93_1723542329682.jpg",
    "ep": 1,
    "s": 261,
    "geo": [
      35.5368,
      139.6868
    ],
    "origin": "Anitabi@Lilin",
    "originURL": "https://anitabi.cn/"
  },
  {
    "id": "jy4fy3evg",
    "cn": "aka aka美发沙龙",
    "name": "aka aka",
    "image": "https://image.xinu.ink/pic/data/873/images/jy4fy3evg-1723382163807.jpg",
    "ep": 1,
    "s": 271,
    "geo": [
      35.537,
      139.6844
    ],
    "origin": "@世界第一托尔厨",
    "originLink": "https://maps.app.goo.gl/hk7icWs6nVBkDbsd6"
  },
  {
    "id": "n6epy3kz7",
    "name": "矢向湯",
    "image": "https://image.xinu.ink/pic/data/873/images/n6epy3kz7_1723531073816.jpg",
    "ep": 1,
    "s": 273,
    "geo": [
      35.537,
      139.6839
    ],
    "origin": "Anitabi@月即别",
    "originURL": "https://anitabi.cn/"
  },
  {
    "id": "jy4160jzy",
    "name": "有限会社 サイトウ住装",
    "image": "https://image.xinu.ink/pic/data/873/images/jy4160jzy-1737818334597.jpg",
    "ep": 1,
    "s": 278,
    "geo": [
      35.5399,
      139.6832
    ],
    "origin": "@世界第一托尔厨",
    "originLink": "https://maps.app.goo.gl/N4rD72UdmNWAQJeu6"
  },
  {
    "id": "jy4d9dbfq",
    "cn": "仁菜拖箱子路过的十字路口",
    "name": "Mimieden",
    "image": "https://image.xinu.ink/pic/data/873/images/jy4d9dbfq-1720111992743.jpg",
    "ep": 1,
    "s": 279,
    "geo": [
      35.5401,
      139.6846
    ],
    "origin": "@世界第一托尔厨",
    "originLink": "https://maps.app.goo.gl/v8T1qQ8ikCKT1C5n6"
  },
  {
    "id": "pd91lom2s",
    "name": "Mimieden",
    "image": "https://image.xinu.ink/pic/data/873/images/pd91lom2s_1729709411835.jpg",
    "ep": 1,
    "s": 281,
    "geo": [
      35.5401,
      139.6847
    ],
    "origin": "Anitabi@Lilin",
    "originURL": "https://anitabi.cn/"
  },
  {
    "id": "n94l4o64p",
    "name": "そば処相馬",
    "image": "https://image.xinu.ink/pic/data/873/images/n94l4o64p_1723744039842.jpg",
    "ep": 1,
    "s": 283,
    "geo": [
      35.5401,
      139.6856
    ],
    "origin": "@kobaya",
    "originLink": "https://www.google.com/maps/d/u/0/edit?mid=1MHZGV3AafVleHD6pVEo5qp_sUZYI9l8&usp=sharing"
  },
  {
    "id": "n6ermu4ca",
    "name": "丸福珈琲店 川崎アゼリア店",
    "image": "https://image.xinu.ink/pic/data/873/images/n6ermu4ca_1723531174966.jpg",
    "ep": 1,
    "s": 355,
    "geo": [
      35.5304,
      139.6985
    ],
    "origin": "Anitabi@月即别",
    "originURL": "https://anitabi.cn/"
  },
  {
    "id": "n6et6uql0",
    "name": "川崎アゼリア",
    "image": "https://image.xinu.ink/pic/data/873/images/n6et6uql0_1723531220471.jpg",
    "ep": 1,
    "s": 416,
    "geo": [
      35.5308,
      139.6977
    ],
    "origin": "Anitabi@月即别",
    "originURL": "https://anitabi.cn/"
  },
  {
    "id": "nde7c8ak3",
    "name": "川崎アゼリア エスカレーター",
    "image": "https://image.xinu.ink/pic/data/873/images/nde7c8ak3_1724078424102.jpg",
    "ep": 1,
    "s": 420,
    "geo": [
      35.5308,
      139.698
    ],
    "origin": "Anitabi@Lilin",
    "originURL": "https://anitabi.cn/"
  },
  {
    "id": "n6euaj159",
    "name": "仁菜と桃香出会い場所",
    "image": "https://image.xinu.ink/pic/data/873/images/n6euaj159_1723531283863.jpg",
    "ep": 1,
    "s": 513,
    "geo": [
      35.5305,
      139.6981
    ],
    "origin": "Anitabi@月即别",
    "originURL": "https://anitabi.cn/"
  },
  {
    "id": "n709b15y5",
    "name": "仲見世通り 信号",
    "image": "https://image.xinu.ink/pic/data/873/images/n709b15y5_1723577886404.jpg",
    "ep": 1,
    "s": 567,
    "geo": [
      35.5302,
      139.6987
    ],
    "origin": "Anitabi@Lilin",
    "originURL": "https://anitabi.cn/"
  },
  {
    "id": "n6ev93jui",
    "name": "仲見世通り",
    "image": "https://image.xinu.ink/pic/data/873/images/n6ev93jui_1723531332599.jpg",
    "ep": 1,
    "s": 576,
    "geo": [
      35.53,
      139.6988
    ],
    "origin": "Anitabi@月即别",
    "originURL": "https://anitabi.cn/"
  },
  {
    "id": "n6ew9nsts",
    "name": "川崎区 元木",
    "image": "https://image.xinu.ink/pic/data/873/images/n6ew9nsts_1723531409487.jpg",
    "ep": 1,
    "s": 598,
    "geo": [
      35.5238,
      139.6971
    ],
    "origin": "Anitabi@月即别",
    "originURL": "https://anitabi.cn/"
  },
  {
    "id": "jfzj2plbr",
    "cn": "吉野家川崎西口店",
    "name": "吉野家川崎西口店",
    "image": "https://image.xinu.ink/pic/data/873/images/jfzj2plbr-1712997158564.jpg",
    "ep": 1,
    "s": 618,
    "geo": [
      35.5316,
      139.6924
    ],
    "origin": "Anitabi@京都紫菜",
    "originURL": "https://anitabi.cn/"
  },
  {
    "id": "pdb3u45ou",
    "cn": "吉野家川崎西口店 店内",
    "name": "吉野家川崎西口店 店内",
    "image": "https://image.xinu.ink/pic/data/873/images/pdb3u45ou_1729713907304.jpg",
    "ep": 1,
    "s": 619,
    "geo": [
      35.5317,
      139.6924
    ],
    "origin": "Anitabi@Lilin",
    "originURL": "https://anitabi.cn/"
  },
  {
    "id": "n6wf7d031",
    "name": "Azalea Information Counter(Azalea Card Counter)",
    "image": "https://image.xinu.ink/pic/data/873/images/n6wf7d031_1723569535163.jpg",
    "ep": 1,
    "s": 854,
    "geo": [
      35.5305,
      139.6981
    ],
    "origin": "Anitabi@Lilin",
    "originURL": "https://anitabi.cn/"
  },
  {
    "id": "j8knqovq4",
    "name": "南河原公園 なかよし丸",
    "image": "https://image.xinu.ink/pic/data/873/images/j8knqovq4-1723384696302.jpg",
    "ep": 1,
    "s": 1085,
    "geo": [
      35.5361,
      139.6881
    ],
    "origin": "Anitabi@Lilin",
    "originURL": "https://anitabi.cn/"
  },
  {
    "id": "n6wpq66od",
    "cn": "大迴音 川崎东口站前店",
    "name": "カラオケ ビッグエコー川崎東口駅前店",
    "image": "https://image.xinu.ink/pic/data/873/images/n6wpq66od_1723570175511.jpg",
    "ep": 1,
    "s": 1129,
    "geo": [
      35.5308,
      139.6994
    ],
    "origin": "Anitabi@Lilin",
    "originURL": "https://anitabi.cn/"
  },
  {
    "id": "n6yqraltl",
    "name": "オーベルグランディオ川崎公開空地",
    "image": "https://image.xinu.ink/pic/data/873/images/n6yqraltl_1723574587896.jpg",
    "ep": 1,
    "s": 1238,
    "geo": [
      35.5388,
      139.687
    ],
    "origin": "Anitabi@Lilin",
    "originURL": "https://anitabi.cn/"
  },
  {
    "id": "n6jz7pja6",
    "name": "さいわい緑道 入口信号",
    "image": "https://image.xinu.ink/pic/data/873/images/n6jz7pja6_1723542502129.jpg",
    "ep": 1,
    "s": 1241,
    "geo": [
      35.5372,
      139.6881
    ],
    "origin": "Anitabi@Lilin",
    "originURL": "https://anitabi.cn/"
  },
  {
    "id": "n4lpqbnoh",
    "name": "中幸町4丁目信号",
    "image": "https://image.xinu.ink/pic/data/873/images/n4lpqbnoh-1723389517312.jpg",
    "ep": 1,
    "s": 1244,
    "geo": [
      35.5316,
      139.6918
    ],
    "origin": "Anitabi@Lilin",
    "originURL": "https://anitabi.cn/"
  },
  {
    "id": "n4jksqnb1",
    "cn": "MUZA川崎 自动扶梯",
    "name": "ミューザ川崎 エスカレーター",
    "image": "https://image.xinu.ink/pic/data/873/images/n4jksqnb1-1723384896691.jpg",
    "ep": 1,
    "s": 1247,
    "geo": [
      35.5315,
      139.6943
    ],
    "origin": "Anitabi@Lilin",
    "originURL": "https://anitabi.cn/"
  },
  {
    "id": "ltrqgglst",
    "cn": "MUZA川崎 人行高架步道",
    "name": "ミューザ川崎 ペデストリアンデッキ",
    "image": "https://image.xinu.ink/pic/data/873/images/ltrqgglst-1719719539130.jpg",
    "ep": 1,
    "s": 1248,
    "geo": [
      35.5309,
      139.6956
    ],
    "origin": "Anitabi@Lilin",
    "originURL": "https://anitabi.cn/"
  },
  {
    "id": "ndenfhjwi",
    "name": "ラゾーナ川崎プラザ",
    "image": "https://image.xinu.ink/pic/data/873/images/ndenfhjwi_1724079395610.jpg",
    "ep": 1,
    "s": 1259,
    "geo": [
      35.5326,
      139.6962
    ],
    "origin": "Anitabi@Lilin",
    "originURL": "https://anitabi.cn/"
  },
  {
    "id": "n6k1y44bk",
    "name": "ラゾーナ川崎プラザ 2階入口",
    "image": "https://image.xinu.ink/pic/data/873/images/n6k1y44bk_1723542713531.jpg",
    "ep": 1,
    "s": 1260,
    "geo": [
      35.532,
      139.6962
    ],
    "origin": "Anitabi@Lilin",
    "originURL": "https://anitabi.cn/"
  },
  {
    "id": "n4klvgq0f",
    "name": "JR川崎駅中央南改札内",
    "image": "https://image.xinu.ink/pic/data/873/images/n4klvgq0f-1723387133329.jpg",
    "ep": 1,
    "s": 1261,
    "geo": [
      35.5314,
      139.6967
    ],
    "origin": "Anitabi@Lilin",
    "originURL": "https://anitabi.cn/"
  },
  {
    "id": "n5se9m7n8",
    "name": "駿台予備学校 仙台校",
    "image": "https://image.xinu.ink/pic/data/873/images/n5se9m7n8_1723482413715.jpg",
    "ep": 2,
    "s": 169,
    "geo": [
      38.2581,
      140.884
    ],
    "origin": "Anitabi@Lilin",
    "originURL": "https://anitabi.cn/"
  },
  {
    "id": "ndaj7edjf",
    "name": "大井町駅 2番線ホーム",
    "image": "https://image.xinu.ink/pic/data/873/images/ndaj7edjf_1724070446474.jpg",
    "ep": 2,
    "s": 221,
    "geo": [
      35.6071,
      139.735
    ],
    "origin": "Anitabi@Lilin",
    "originURL": "https://anitabi.cn/"
  },
  {
    "id": "n6hn4qunm",
    "name": "大井町駅",
    "image": "https://image.xinu.ink/pic/data/873/images/n6hn4qunm_1723537438717.jpg",
    "ep": 2,
    "s": 236,
    "geo": [
      35.607,
      139.7349
    ],
    "origin": "Anitabi@月即别",
    "originURL": "https://anitabi.cn/"
  },
  {
    "id": "jfxogwfyf",
    "cn": "南武线矢向站",
    "name": "矢向駅",
    "image": "https://image.xinu.ink/pic/data/873/images/jfxogwfyf-1712993130857.jpg",
    "ep": 2,
    "s": 335,
    "geo": [
      35.5386,
      139.6804
    ],
    "origin": "Anitabi@京都紫菜",
    "originURL": "https://anitabi.cn/"
  },
  {
    "id": "n6xjshnzg",
    "cn": "TimeSpace停车场 川崎幸町",
    "name": "タイムスペース川崎幸町",
    "image": "https://image.xinu.ink/pic/data/873/images/n6xjshnzg_1723571987104.jpg",
    "ep": 2,
    "s": 673,
    "geo": [
      35.5373,
      139.6987
    ],
    "origin": "Anitabi@Lilin",
    "originURL": "https://anitabi.cn/"
  },
  {
    "id": "n6xma5541",
    "name": "多摩川見晴らし公園",
    "image": "https://image.xinu.ink/pic/data/873/images/n6xma5541_1723572337327.jpg",
    "ep": 2,
    "s": 680,
    "geo": [
      35.5376,
      139.6995
    ],
    "origin": "Anitabi@Lilin",
    "originURL": "https://anitabi.cn/"
  },
  {
    "id": "n93k98q40",
    "name": "六郷川橋梁(JR)",
    "image": "https://image.xinu.ink/pic/data/873/images/n93k98q40_1723741810557.jpg",
    "ep": 2,
    "s": 688,
    "geo": [
      35.5369,
      139.703
    ],
    "origin": "Anitabi@Lilin",
    "originURL": "https://anitabi.cn/"
  },
  {
    "id": "lysnv8rqe",
    "name": "仁菜家の位置",
    "image": "https://image.xinu.ink/pic/data/873/images/lysnv8rqe-1720113334957.jpg",
    "ep": 2,
    "s": 781,
    "geo": [
      35.5407,
      139.6862
    ],
    "origin": "@ねぎ太",
    "originLink": "https://negitap.hateblo.jp/entry/2024/05/02/002403#309"
  },
  {
    "id": "n6hpanjyv",
    "name": "鍋ぞう川崎店",
    "image": "https://image.xinu.ink/pic/data/873/images/n6hpanjyv_1723537600036.jpg",
    "ep": 2,
    "s": 975,
    "geo": [
      35.5287,
      139.698
    ],
    "origin": "Anitabi@月即别",
    "originURL": "https://anitabi.cn/"
  },
  {
    "id": "ozu3v1szy",
    "name": "浄土真宗本願寺派正楽寺前",
    "image": "https://image.xinu.ink/pic/data/873/images/ozu3v1szy_1728658191348.jpg",
    "ep": 2,
    "s": 1139,
    "geo": [
      35.5335,
      139.6905
    ],
    "origin": "Anitabi@Lilin",
    "originURL": "https://anitabi.cn/"
  },
  {
    "id": "n6je2ckzk",
    "name": "諏訪公園前",
    "image": "https://image.xinu.ink/pic/data/873/images/n6je2ckzk_1723541167007.jpg",
    "ep": 2,
    "s": 1145,
    "geo": [
      35.5348,
      139.6906
    ],
    "origin": "Anitabi@Lilin",
    "originURL": "https://anitabi.cn/"
  },
  {
    "id": "lytiv6if2",
    "name": "桃香家の外",
    "image": "https://image.xinu.ink/pic/data/873/images/lytiv6if2-1720115200366.jpg",
    "ep": 3,
    "s": 370,
    "geo": [
      35.5358,
      139.6908
    ],
    "origin": "Anitabi@うに",
    "originURL": "https://anitabi.cn/"
  },
  {
    "id": "ndiiw56jh",
    "name": "桃香家の隣",
    "image": "https://image.xinu.ink/pic/data/873/images/ndiiw56jh_1724087867350.jpg",
    "ep": 3,
    "s": 429,
    "geo": [
      35.5357,
      139.6898
    ],
    "origin": "Anitabi@Lilin",
    "originURL": "https://anitabi.cn/"
  },
  {
    "id": "n6hx1txaa",
    "name": "渋谷駅前",
    "image": "https://image.xinu.ink/pic/data/873/images/n6hx1txaa_1723537989030.jpg",
    "ep": 3,
    "s": 461,
    "geo": [
      35.6588,
      139.7002
    ],
    "origin": "Anitabi@月即别",
    "originURL": "https://anitabi.cn/"
  },
  {
    "id": "nd9gwj5fy",
    "name": "忠犬ハチ公",
    "image": "https://image.xinu.ink/pic/data/873/images/nd9gwj5fy_1724068118434.jpg",
    "ep": 3,
    "s": 465,
    "geo": [
      35.659,
      139.7005
    ],
    "origin": "Anitabi@Lilin",
    "originURL": "https://anitabi.cn/"
  },
  {
    "id": "nd9hxolrs",
    "name": "渋谷スクランブル交差点",
    "image": "https://image.xinu.ink/pic/data/873/images/nd9hxolrs_1724068188139.jpg",
    "ep": 3,
    "s": 471,
    "geo": [
      35.6595,
      139.7
    ],
    "origin": "Anitabi@Lilin",
    "originURL": "https://anitabi.cn/"
  },
  {
    "id": "nd9kliynq",
    "name": "mineo渋谷",
    "image": "https://image.xinu.ink/pic/data/873/images/nd9kliynq_1724068347637.jpg",
    "ep": 3,
    "s": 474,
    "geo": [
      35.66,
      139.6997
    ],
    "origin": "Anitabi@Lilin",
    "originURL": "https://anitabi.cn/"
  },
  {
    "id": "nd9meeitp",
    "cn": "Outback Steakhouse 涩谷店",
    "name": "アウトバックステーキ ステーキハウス 渋谷店",
    "image": "https://image.xinu.ink/pic/data/873/images/nd9meeitp_1724068451972.jpg",
    "ep": 3,
    "s": 475,
    "geo": [
      35.6613,
      139.697
    ],
    "origin": "Anitabi@Lilin",
    "originURL": "https://anitabi.cn/"
  },
  {
    "id": "nd9p0vab1",
    "name": "HangOut HangOver Shibuya",
    "image": "https://image.xinu.ink/pic/data/873/images/nd9p0vab1_1724068611216.jpg",
    "ep": 3,
    "s": 477,
    "geo": [
      35.6618,
      139.7003
    ],
    "origin": "Anitabi@Lilin",
    "originURL": "https://anitabi.cn/"
  },
  {
    "id": "jtpiwne26",
    "cn": "大迴音 涩谷中心街本店",
    "name": "カラオケ ビッグエコー渋谷センター街本店",
    "image": "https://image.xinu.ink/pic/data/873/images/jtpiwne26-1714072479428.jpg",
    "ep": 3,
    "s": 478,
    "geo": [
      35.6599,
      139.7
    ],
    "origin": "@世界第一托尔厨",
    "originLink": "https://maps.app.goo.gl/z4S2mHMtq6xV5ikH7"
  },
  {
    "id": "nd9sz1sha",
    "name": "さくら坂",
    "image": "https://image.xinu.ink/pic/data/873/images/nd9sz1sha_1724068849298.jpg",
    "ep": 3,
    "s": 480,
    "geo": [
      35.6565,
      139.7008
    ],
    "origin": "Anitabi@Lilin",
    "originURL": "https://anitabi.cn/"
  },
  {
    "id": "nchdgbmul",
    "cn": "Mos Burger 涩谷道玄坂店",
    "name": "モスバーガー渋谷道玄坂店",
    "image": "https://image.xinu.ink/pic/data/873/images/nchdgbmul_1724006959612.jpg",
    "ep": 3,
    "s": 599,
    "geo": [
      35.6592,
      139.6979
    ],
    "origin": "Anitabi@Lilin",
    "originURL": "https://anitabi.cn/"
  },
  {
    "id": "n4jghr03n",
    "name": "チネチッタ通り入口",
    "image": "https://image.xinu.ink/pic/data/873/images/n4jghr03n-1723384581994.jpg",
    "ep": 3,
    "s": 614,
    "geo": [
      35.5289,
      139.6987
    ],
    "origin": "Anitabi@Lilin",
    "originURL": "https://anitabi.cn/"
  },
  {
    "id": "nchbvmpu5",
    "cn": "西班牙坂",
    "name": "スペイン坂",
    "image": "https://image.xinu.ink/pic/data/873/images/nchbvmpu5_1724006865426.jpg",
    "ep": 3,
    "s": 711,
    "geo": [
      35.6615,
      139.6988
    ],
    "origin": "Anitabi@Lilin",
    "originURL": "https://anitabi.cn/"
  },
  {
    "id": "jtni8equ2",
    "cn": "川崎Lazona广场舞台",
    "name": "Lazona Kawasaki Plaza Stage",
    "image": "https://image.xinu.ink/pic/data/873/images/jtni8equ2-1714068114712.jpg",
    "ep": 3,
    "s": 1201,
    "geo": [
      35.5322,
      139.6959
    ],
    "origin": "@世界第一托尔厨",
    "originLink": "https://www.google.com/maps/d/edit?hl=zh-CN&mid=1eNSBc8cHUr-G6NHNahY9hyjez4vmdHo&ll=35.53593790424341%2C139.68940243736066&z=18"
  },
  {
    "id": "n6kgq02b5",
    "name": "ラゾーナ川崎プラザ ルーファー広場 グランドステージ",
    "image": "https://image.xinu.ink/pic/data/873/images/n6kgq02b5_1723543503374.jpg",
    "ep": 3,
    "s": 1252,
    "geo": [
      35.5321,
      139.6957
    ],
    "origin": "Anitabi@Lilin",
    "originURL": "https://anitabi.cn/"
  },
  {
    "id": "n6kj2styg",
    "name": "ラゾーナ川崎プラザ ルーファー広場",
    "image": "https://image.xinu.ink/pic/data/873/images/n6kj2styg_1723543656533.jpg",
    "ep": 3,
    "s": 1269,
    "geo": [
      35.5323,
      139.6958
    ],
    "origin": "Anitabi@Lilin",
    "originURL": "https://anitabi.cn/"
  },
  {
    "id": "pda6kp30k",
    "name": "島村楽器 ラゾーナ川崎店",
    "image": "https://image.xinu.ink/pic/data/873/images/pda6kp30k_1729711890737.jpg",
    "ep": 4,
    "s": 12,
    "geo": [
      35.5333,
      139.6954
    ],
    "origin": "Anitabi@Lilin",
    "originURL": "https://anitabi.cn/"
  },
  {
    "id": "jux4mmoio",
    "cn": "岛村乐器川崎Lazona分店",
    "name": "島村楽器 ラゾーナ川崎店",
    "image": "https://image.xinu.ink/pic/data/873/images/jux4mmoio-1714167603800.jpg",
    "ep": 4,
    "s": 54,
    "geo": [
      35.5332,
      139.6952
    ],
    "origin": "@世界第一托尔厨",
    "originLink": "https://maps.app.goo.gl/viKX81di4mX4dTgo9"
  },
  {
    "id": "jux15agv6",
    "cn": "HMV川崎Lazona分店",
    "name": "HMVラゾーナ川崎",
    "image": "https://image.xinu.ink/pic/data/873/images/jux15agv6-1714167218039.jpg",
    "ep": 4,
    "s": 77,
    "geo": [
      35.533,
      139.6952
    ],
    "origin": "@世界第一托尔厨",
    "originLink": "https://maps.app.goo.gl/aUvATe4zfLmmcNcj7"
  },
  {
    "id": "juwx8oy76",
    "cn": "Renoir咖啡馆",
    "name": "喫茶室ルノアール 渋谷東急ハンズ前店",
    "image": "https://image.xinu.ink/pic/data/873/images/juwx8oy76-1714166957812.jpg",
    "ep": 4,
    "s": 543,
    "geo": [
      35.662,
      139.6972
    ],
    "origin": "@世界第一托尔厨",
    "originLink": "https://maps.app.goo.gl/W3xUirjZzdzQ3z3DA"
  },
  {
    "id": "nda42fj9q",
    "name": "都立石神井公園",
    "image": "https://image.xinu.ink/pic/data/873/images/nda42fj9q_1724069517232.jpg",
    "ep": 4,
    "s": 800,
    "geo": [
      35.7394,
      139.6013
    ],
    "origin": "Anitabi@Lilin",
    "originURL": "https://anitabi.cn/"
  },
  {
    "id": "ndaw9mty4",
    "cn": "Pacific Royal Court M.M. Urban Tower",
    "name": "パシフィックロイヤルコートみなとみらいアーバンタワー",
    "image": "https://image.xinu.ink/pic/data/873/images/ndaw9mty4_1724071222106.jpg",
    "ep": 4,
    "s": 882,
    "geo": [
      35.4626,
      139.6311
    ],
    "origin": "@kobaya",
    "originLink": "https://www.google.com/maps/d/u/0/edit?mid=1MHZGV3AafVleHD6pVEo5qp_sUZYI9l8&usp=sharing"
  },
  {
    "id": "ndh7i6y3j",
    "cn": "Live House Serbian Night",
    "name": "セルビアンナイト",
    "image": "https://image.xinu.ink/pic/data/873/images/ndh7i6y3j_1724084968131.jpg",
    "ep": 5,
    "s": 146,
    "geo": [
      35.528,
      139.6999
    ],
    "origin": "Anitabi@Lilin",
    "originURL": "https://anitabi.cn/"
  },
  {
    "id": "n6wxu7kw5",
    "name": "川崎銀座街",
    "image": "https://image.xinu.ink/pic/data/873/images/n6wxu7kw5_1723570659686.jpg",
    "ep": 5,
    "s": 384,
    "geo": [
      35.5312,
      139.7006
    ],
    "origin": "Anitabi@Lilin",
    "originURL": "https://anitabi.cn/"
  },
  {
    "id": "n4kqm0zvn",
    "name": "中華料理 天龍 銀座街店",
    "image": "https://image.xinu.ink/pic/data/873/images/n4kqm0zvn-1723387442836.jpg",
    "ep": 5,
    "s": 402,
    "geo": [
      35.531,
      139.7005
    ],
    "origin": "Anitabi@Lilin",
    "originURL": "https://anitabi.cn/"
  },
  {
    "id": "ncf9qshbj",
    "name": "Tokyo Dome City Hall",
    "image": "https://image.xinu.ink/pic/data/873/images/ncf9qshbj_1724002380071.jpg",
    "ep": 5,
    "s": 505,
    "geo": [
      35.7033,
      139.7541
    ],
    "origin": "Anitabi@Lilin",
    "originURL": "https://anitabi.cn/"
  },
  {
    "id": "n4l1jfkt6",
    "name": "やきとり 串揚げ 登利亭",
    "image": "https://image.xinu.ink/pic/data/873/images/n4l1jfkt6-1723388116677.jpg",
    "ep": 5,
    "s": 769,
    "geo": [
      35.5296,
      139.6997
    ],
    "origin": "Anitabi@Lilin",
    "originURL": "https://anitabi.cn/"
  },
  {
    "id": "ndei1cv24",
    "name": "マモール川崎",
    "image": "https://image.xinu.ink/pic/data/873/images/ndei1cv24_1724079069743.jpg",
    "ep": 5,
    "s": 1065,
    "geo": [
      35.5323,
      139.6925
    ],
    "origin": "Anitabi@Lilin",
    "originURL": "https://anitabi.cn/"
  },
  {
    "id": "kf8wn5tp8",
    "name": "河原町団地13号棟",
    "image": "https://image.xinu.ink/pic/data/873/images/kf8wn5tp8-1723532548341.jpg",
    "ep": 6,
    "s": 12,
    "geo": [
      35.54,
      139.6921
    ],
    "origin": "Anitabi@Lilin",
    "originURL": "https://anitabi.cn/"
  },
  {
    "id": "n4je9a35c",
    "name": "かわしんふれあい広場",
    "image": "https://image.xinu.ink/pic/data/873/images/n4je9a35c-1723384483264.jpg",
    "ep": 6,
    "s": 619,
    "geo": [
      35.5299,
      139.7011
    ],
    "origin": "Anitabi@Lilin",
    "originURL": "https://anitabi.cn/"
  },
  {
    "id": "n4jnv1iy7",
    "name": "ミューザ川崎 ゲートプラザ",
    "image": "https://image.xinu.ink/pic/data/873/images/n4jnv1iy7-1723385121506.jpg",
    "ep": 6,
    "s": 620,
    "geo": [
      35.531,
      139.6953
    ],
    "origin": "Anitabi@Lilin",
    "originURL": "https://anitabi.cn/"
  },
  {
    "id": "rdnsaxbfr",
    "cn": "多摩川见晴公园",
    "name": "多摩川見晴らし公園",
    "image": "https://image.xinu.ink/pic/data/873/images/rdnsaxbfr-1735384005247.jpg",
    "ep": 6,
    "s": 621,
    "geo": [
      35.5374,
      139.7001
    ],
    "origin": "Anitabi@和泉Ciao",
    "originURL": "https://anitabi.cn/"
  },
  {
    "id": "ndi1c881g",
    "name": "河原町団地14号棟",
    "image": "https://image.xinu.ink/pic/data/873/images/ndi1c881g_1724086772098.jpg",
    "ep": 6,
    "s": 752,
    "geo": [
      35.5395,
      139.6921
    ],
    "origin": "Anitabi@Lilin",
    "originURL": "https://anitabi.cn/"
  },
  {
    "id": "ndac3pyjj",
    "name": "武道館",
    "image": "https://image.xinu.ink/pic/data/873/images/ndac3pyjj_1724070005817.jpg",
    "ep": 6,
    "s": 958,
    "geo": [
      35.6937,
      139.749
    ],
    "origin": "Anitabi@Lilin",
    "originURL": "https://anitabi.cn/"
  },
  {
    "id": "kf9mfhjeg",
    "cn": "武道馆",
    "name": "武道館",
    "image": "https://image.xinu.ink/pic/data/873/images/kf9mfhjeg-1715761916543.jpg",
    "ep": 6,
    "s": 965,
    "geo": [
      35.693,
      139.7491
    ]
  },
  {
    "id": "nchksb68s",
    "name": "品川駅 1·2番線ホーム",
    "image": "https://image.xinu.ink/pic/data/873/images/nchksb68s_1724007424225.jpg",
    "ep": 6,
    "s": 992,
    "geo": [
      35.627,
      139.7385
    ],
    "origin": "Anitabi@Lilin",
    "originURL": "https://anitabi.cn/"
  },
  {
    "id": "kobo8xch3",
    "name": "品川駅 2番線",
    "image": "https://image.xinu.ink/pic/data/873/images/kobo8xch3-1716472069327.jpg",
    "ep": 6,
    "s": 1021,
    "geo": [
      35.6269,
      139.7385
    ],
    "originLink": "https://maps.app.goo.gl/m12JDCcKruSrJtvS9"
  },
  {
    "id": "ky5251u65",
    "name": "溝ノ口劇場",
    "image": "https://image.xinu.ink/pic/data/873/images/ky5251u65-1717240856211.jpg",
    "ep": 7,
    "s": 161,
    "geo": [
      35.5984,
      139.6129
    ],
    "origin": "Anitabi@月即别",
    "originURL": "https://anitabi.cn/"
  },
  {
    "id": "kijvuxbjf",
    "name": "EXPASA談合坂",
    "image": "https://image.xinu.ink/pic/data/873/images/kijvuxbjf-1716019354788.jpg",
    "ep": 7,
    "s": 626,
    "geo": [
      35.6325,
      139.0639
    ],
    "origin": "Anitabi@月即别",
    "originURL": "https://anitabi.cn/"
  },
  {
    "id": "ndb79xuck",
    "name": "EXPASA談合坂 駐車場",
    "image": "https://image.xinu.ink/pic/data/873/images/ndb79xuck_1724071888437.jpg",
    "ep": 7,
    "s": 629,
    "geo": [
      35.6325,
      139.0642
    ],
    "origin": "Anitabi@Lilin",
    "originURL": "https://anitabi.cn/"
  },
  {
    "id": "ndco6i3kb",
    "name": "JR上諏訪駅前",
    "image": "https://image.xinu.ink/pic/data/873/images/ndco6i3kb_1724075100967.jpg",
    "ep": 7,
    "s": 755,
    "geo": [
      36.0468,
      138.1168
    ],
    "origin": "Anitabi@Lilin",
    "originURL": "https://anitabi.cn/"
  },
  {
    "id": "klqztns9d",
    "cn": "诹访中央停车场",
    "name": "諏訪中央駐車場",
    "image": "https://image.xinu.ink/pic/data/873/images/klqztns9d-1716269954241.jpg",
    "ep": 7,
    "s": 757,
    "geo": [
      36.0441,
      138.1188
    ],
    "originLink": "https://maps.app.goo.gl/XPwW7Qgq6dVa6iAa9"
  },
  {
    "id": "ndc7tvnux",
    "name": "诹访湖畔公园",
    "image": "https://image.xinu.ink/pic/data/873/images/ndc7tvnux_1724074099282.jpg",
    "ep": 7,
    "s": 773,
    "geo": [
      36.0476,
      138.1105
    ],
    "origin": "Anitabi@Lilin",
    "originURL": "https://anitabi.cn/"
  },
  {
    "id": "ndcaicic9",
    "name": "焼鳥旬魚 二鳥目",
    "image": "https://image.xinu.ink/pic/data/873/images/ndcaicic9_1724074257246.jpg",
    "ep": 7,
    "s": 954,
    "geo": [
      36.0437,
      138.1179
    ],
    "origin": "Anitabi@Lilin",
    "originURL": "https://anitabi.cn/"
  },
  {
    "id": "ndccxc7k7",
    "name": "ヤマトビル",
    "image": "https://image.xinu.ink/pic/data/873/images/ndccxc7k7_1724074403013.jpg",
    "ep": 7,
    "s": 1039,
    "geo": [
      36.0437,
      138.1175
    ],
    "origin": "Anitabi@Lilin",
    "originURL": "https://anitabi.cn/"
  },
  {
    "id": "nddiqrtwd",
    "name": "創開碑",
    "image": "https://image.xinu.ink/pic/data/873/images/nddiqrtwd_1724076932157.jpg",
    "ep": 7,
    "s": 1085,
    "geo": [
      36.0438,
      138.1177
    ],
    "origin": "Anitabi@Lilin",
    "originURL": "https://anitabi.cn/"
  },
  {
    "id": "ky55sd3ie",
    "name": "柳並公園",
    "image": "https://image.xinu.ink/pic/data/873/images/ky55sd3ie-1717241058612.jpg",
    "ep": 7,
    "s": 1134,
    "geo": [
      36.0445,
      138.1164
    ],
    "origin": "Anitabi@月即别",
    "originURL": "https://anitabi.cn/"
  },
  {
    "id": "ndc1y9fzf",
    "name": "諏訪市湖畔公園",
    "image": "https://image.xinu.ink/pic/data/873/images/ndc1y9fzf_1724073759347.jpg",
    "ep": 7,
    "s": 1151,
    "geo": [
      36.0477,
      138.1104
    ],
    "origin": "Anitabi@Lilin",
    "originURL": "https://anitabi.cn/"
  },
  {
    "id": "kqjdhkck6",
    "cn": "北海道旭川北高等学校（花咲スポーツ公園 球技場）",
    "name": "旭川北高",
    "image": "https://image.xinu.ink/pic/data/873/images/kqjdhkck6-1716645180512.jpg",
    "ep": 8,
    "s": 49,
    "geo": [
      43.7887,
      142.3706
    ]
  },
  {
    "id": "kpkabqzub",
    "name": " NEXCO中日本 談合坂",
    "image": "https://image.xinu.ink/pic/data/873/images/kpkabqzub-1716568973349.jpg",
    "ep": 8,
    "s": 210,
    "geo": [
      35.6277,
      139.0455
    ],
    "origin": "Anitabi@月即别",
    "originURL": "https://anitabi.cn/"
  },
  {
    "id": "n4is5i65y",
    "cn": "Brillia e-Square 红色邮箱",
    "name": "ブリリアイースクエア 赤い郵便箱",
    "image": "https://image.xinu.ink/pic/data/873/images/n4is5i65y-1723383160094.jpg",
    "ep": 8,
    "s": 636,
    "geo": [
      35.5402,
      139.6864
    ],
    "origin": "Anitabi@Lilin",
    "originURL": "https://anitabi.cn/"
  },
  {
    "id": "ky5bx3bh6",
    "cn": "多摩川SkyBridge",
    "name": "多摩川スカイブリッジ",
    "image": "https://image.xinu.ink/pic/data/873/images/ky5bx3bh6-1717241612196.jpg",
    "ep": 8,
    "s": 740,
    "geo": [
      35.5419,
      139.7618
    ],
    "origin": "Anitabi@月即别",
    "originURL": "https://anitabi.cn/"
  },
  {
    "id": "ky5l6gww6",
    "name": "Zepp Haneda",
    "image": "https://image.xinu.ink/pic/data/873/images/ky5l6gww6-1717241996875.jpg",
    "ep": 8,
    "s": 816,
    "geo": [
      35.5473,
      139.7567
    ],
    "origin": "Anitabi@月即别",
    "originURL": "https://anitabi.cn/"
  },
  {
    "id": "ncgatcng2",
    "name": "Zepp Haneda 舞台裏",
    "image": "https://image.xinu.ink/pic/data/873/images/ncgatcng2_1724004669974.jpg",
    "ep": 8,
    "s": 824,
    "geo": [
      35.5477,
      139.7563
    ],
    "origin": "Anitabi@Lilin",
    "originURL": "https://anitabi.cn/"
  },
  {
    "id": "ncgl5u3xm",
    "name": "Zepp Haneda 駐車場",
    "image": "https://image.xinu.ink/pic/data/873/images/ncgl5u3xm_1724005249311.jpg",
    "ep": 8,
    "s": 1008,
    "geo": [
      35.5475,
      139.7568
    ],
    "origin": "Anitabi@Lilin",
    "originURL": "https://anitabi.cn/"
  },
  {
    "id": "nch1vw4gs",
    "name": "Zepp Haneda 駐車場出口",
    "image": "https://image.xinu.ink/pic/data/873/images/nch1vw4gs_1724006257893.jpg",
    "ep": 8,
    "s": 1129,
    "geo": [
      35.5474,
      139.7561
    ],
    "origin": "Anitabi@Lilin",
    "originURL": "https://anitabi.cn/"
  },
  {
    "id": "ndid65pe9",
    "name": "神明町児童遊園",
    "image": "https://image.xinu.ink/pic/data/873/images/ndid65pe9_1724087485736.jpg",
    "ep": 9,
    "s": 590,
    "geo": [
      35.5393,
      139.6915
    ],
    "origin": "Anitabi@Lilin",
    "originURL": "https://anitabi.cn/"
  },
  {
    "id": "nbd8y4105",
    "name": "樂水橋",
    "image": "https://image.xinu.ink/pic/data/873/images/nbd8y4105_1723919613595.jpg",
    "ep": 9,
    "s": 1032,
    "geo": [
      35.6247,
      139.746
    ],
    "origin": "Anitabi@Lilin",
    "originURL": "https://anitabi.cn/"
  },
  {
    "id": "n4lvz6o3m",
    "name": "CLUB Que Shimokitazawa",
    "image": "https://image.xinu.ink/pic/data/873/images/n4lvz6o3m-1723389900031.jpg",
    "ep": 10,
    "s": 15,
    "geo": [
      35.6608,
      139.6686
    ],
    "origin": "Anitabi@Lilin",
    "originURL": "https://anitabi.cn/"
  },
  {
    "id": "n4lx469is",
    "name": "えくぷり",
    "image": "https://image.xinu.ink/pic/data/873/images/n4lx469is-1723389962179.jpg",
    "ep": 10,
    "s": 159,
    "geo": [
      35.6606,
      139.6683
    ],
    "origin": "Anitabi@Lilin",
    "originURL": "https://anitabi.cn/"
  },
  {
    "id": "nbd4nb9z3",
    "name": "ミカン下北 階段",
    "image": "https://image.xinu.ink/pic/data/873/images/nbd4nb9z3_1723919361621.jpg",
    "ep": 10,
    "s": 243,
    "geo": [
      35.6614,
      139.6682
    ],
    "origin": "Anitabi@Lilin",
    "originURL": "https://anitabi.cn/"
  },
  {
    "id": "nd3vc5xki",
    "name": "熊本駅",
    "image": "https://image.xinu.ink/pic/data/873/images/nd3vc5xki_1724055925438.jpg",
    "ep": 10,
    "s": 593,
    "geo": [
      32.79,
      130.689
    ],
    "origin": "Anitabi@Lilin",
    "originURL": "https://anitabi.cn/"
  },
  {
    "id": "nd3pw9c8w",
    "name": "熊本駅 1番線ホーム",
    "image": "https://image.xinu.ink/pic/data/873/images/nd3pw9c8w_1724055599103.jpg",
    "ep": 10,
    "s": 597,
    "geo": [
      32.79,
      130.6889
    ],
    "origin": "Anitabi@Lilin",
    "originURL": "https://anitabi.cn/"
  },
  {
    "id": "l5j9v5t1n",
    "name": "竜田口駅",
    "image": "https://image.xinu.ink/pic/data/873/images/l5j9v5t1n-1717820362307.jpg",
    "ep": 10,
    "s": 601,
    "geo": [
      32.8204,
      130.7466
    ],
    "origin": "Anitabi@月即别",
    "originURL": "https://anitabi.cn/"
  },
  {
    "id": "lgjl5cfqr",
    "cn": "井芹老家",
    "name": "井芹の実家",
    "image": "https://image.xinu.ink/pic/data/873/images/lgjl5cfqr-1718683041315.jpg",
    "ep": 10,
    "s": 608,
    "geo": [
      32.8522,
      130.7742
    ],
    "origin": "Anitabi@うに",
    "originURL": "https://anitabi.cn/"
  },
  {
    "id": "nd3xxigt2",
    "name": "竜田口駅前",
    "image": "https://image.xinu.ink/pic/data/873/images/nd3xxigt2_1724056082485.jpg",
    "ep": 10,
    "s": 759,
    "geo": [
      32.822,
      130.748
    ],
    "origin": "Anitabi@Lilin",
    "originURL": "https://anitabi.cn/"
  },
  {
    "id": "l5jd35x5y",
    "cn": "新水前寺站前",
    "name": "新水前寺駅前",
    "image": "https://image.xinu.ink/pic/data/873/images/l5jd35x5y-1717820526813.jpg",
    "ep": 10,
    "s": 773,
    "geo": [
      32.7936,
      130.7267
    ],
    "origin": "Anitabi@月即别",
    "originURL": "https://anitabi.cn/"
  },
  {
    "id": "nd3u5bs1t",
    "name": "新水前寺駅前",
    "image": "https://image.xinu.ink/pic/data/873/images/nd3u5bs1t_1724055855572.jpg",
    "ep": 10,
    "s": 776,
    "geo": [
      32.7937,
      130.7265
    ],
    "origin": "Anitabi@Lilin",
    "originURL": "https://anitabi.cn/"
  },
  {
    "id": "n5s8zgx1j",
    "name": "大甲橋",
    "image": "https://image.xinu.ink/pic/data/873/images/n5s8zgx1j_1723482083808.jpg",
    "ep": 10,
    "s": 778,
    "geo": [
      32.802,
      130.7138
    ],
    "origin": "Anitabi@Lilin",
    "originURL": "https://anitabi.cn/"
  },
  {
    "id": "l5jfehvyc",
    "name": "洗馬橋駅",
    "image": "https://image.xinu.ink/pic/data/873/images/l5jfehvyc-1717820678421.jpg",
    "ep": 10,
    "s": 791,
    "geo": [
      32.7991,
      130.6993
    ],
    "origin": "Anitabi@月即别",
    "originURL": "https://anitabi.cn/"
  },
  {
    "id": "nd3oe769u",
    "name": "明午橋",
    "image": "https://image.xinu.ink/pic/data/873/images/nd3oe769u_1724055507721.jpg",
    "ep": 10,
    "s": 1227,
    "geo": [
      32.8065,
      130.7183
    ],
    "origin": "@kobaya",
    "originLink": "https://www.google.com/maps/d/u/0/edit?mid=1MHZGV3AafVleHD6pVEo5qp_sUZYI9l8&usp=sharing"
  },
  {
    "id": "l5mo06wa5",
    "name": "辛島町駅・サンロード新市街",
    "image": "https://image.xinu.ink/pic/data/873/images/l5mo06wa5-1717827802730.jpg",
    "ep": 10,
    "s": 1227,
    "geo": [
      32.799,
      130.705
    ],
    "origin": "Anitabi@月即别",
    "originURL": "https://anitabi.cn/"
  },
  {
    "id": "l5msjkl1d",
    "name": "通町筋駅",
    "image": "https://image.xinu.ink/pic/data/873/images/l5msjkl1d-1717827995385.jpg",
    "ep": 10,
    "s": 1230,
    "geo": [
      32.8032,
      130.7098
    ],
    "origin": "Anitabi@月即别",
    "originURL": "https://anitabi.cn/"
  },
  {
    "id": "ldqwi2f1o",
    "cn": "东扇岛东公园",
    "name": "東扇島東公園",
    "image": "https://image.xinu.ink/pic/data/873/images/ldqwi2f1o_1723478024188.jpg",
    "ep": 11,
    "s": 14,
    "geo": [
      35.5043,
      139.7696
    ],
    "origin": "Anitabi@月即别",
    "originURL": "https://anitabi.cn/"
  },
  {
    "id": "ndhtdbka5",
    "name": "東扇島東公園 潮入の池",
    "image": "https://image.xinu.ink/pic/data/873/images/ndhtdbka5_1724086293634.jpg",
    "ep": 11,
    "s": 276,
    "geo": [
      35.5059,
      139.7717
    ],
    "origin": "Anitabi@Lilin",
    "originURL": "https://anitabi.cn/"
  },
  {
    "id": "n5qwskrw1",
    "name": "サンフラワービル",
    "image": "https://image.xinu.ink/pic/data/873/images/n5qwskrw1_1723479184777.jpg",
    "ep": 12,
    "s": 128,
    "geo": [
      35.7112,
      139.7039
    ],
    "origin": "Anitabi@Lilin",
    "originURL": "https://anitabi.cn/"
  },
  {
    "id": "lyoy0r6mh",
    "name": "平和島駅外",
    "image": "https://image.xinu.ink/pic/data/873/images/lyoy0r6mh-1720105257933.jpg",
    "ep": 12,
    "s": 644,
    "geo": [
      35.5785,
      139.7352
    ],
    "origin": "Anitabi@うに",
    "originURL": "https://anitabi.cn/"
  },
  {
    "id": "lyozai0ee",
    "name": "平和島駅構内",
    "image": "https://image.xinu.ink/pic/data/873/images/lyozai0ee-1720105306521.jpg",
    "ep": 12,
    "s": 647,
    "geo": [
      35.5788,
      139.735
    ],
    "origin": "Anitabi@うに",
    "originURL": "https://anitabi.cn/"
  },
  {
    "id": "n4lzkgao2",
    "cn": "Sound Crew Studio",
    "name": "サウンドクルースタジオ",
    "image": "https://image.xinu.ink/pic/data/873/images/n4lzkgao2-1723390143773.jpg",
    "ep": 12,
    "s": 681,
    "geo": [
      35.576,
      139.7473
    ],
    "origin": "Anitabi@Lilin",
    "originURL": "https://anitabi.cn/"
  },
  {
    "id": "n6yusw6c7",
    "name": "神明神社 手水舎",
    "image": "https://image.xinu.ink/pic/data/873/images/n6yusw6c7_1723574868558.jpg",
    "ep": 12,
    "s": 1053,
    "geo": [
      35.5388,
      139.6874
    ],
    "origin": "Anitabi@Lilin",
    "originURL": "https://anitabi.cn/"
  },
  {
    "id": "n6yyx70ng",
    "name": "神明神社 鳥居内側",
    "image": "https://image.xinu.ink/pic/data/873/images/n6yyx70ng_1723575097245.jpg",
    "ep": 12,
    "s": 1065,
    "geo": [
      35.5388,
      139.6875
    ],
    "origin": "Anitabi@Lilin",
    "originURL": "https://anitabi.cn/"
  },
  {
    "id": "pdc1hlg9q",
    "name": "神明神社 鳥居",
    "image": "https://image.xinu.ink/pic/data/873/images/pdc1hlg9q_1729715940496.jpg",
    "ep": 12,
    "s": 1066,
    "geo": [
      35.5388,
      139.6876
    ],
    "origin": "Anitabi@Lilin",
    "originURL": "https://anitabi.cn/"
  },
  {
    "id": "lyqhsalgi",
    "name": "神明神社外",
    "image": "https://image.xinu.ink/pic/data/873/images/lyqhsalgi-1720108651766.jpg",
    "ep": 12,
    "s": 1076,
    "geo": [
      35.5388,
      139.6876
    ],
    "origin": "Anitabi@うに",
    "originURL": "https://anitabi.cn/"
  },
  {
    "id": "lyqjqw3wf",
    "name": "神明神社境内",
    "image": "https://image.xinu.ink/pic/data/873/images/lyqjqw3wf-1720108726125.jpg",
    "ep": 12,
    "s": 1088,
    "geo": [
      35.5389,
      139.6871
    ],
    "origin": "Anitabi@うに",
    "originURL": "https://anitabi.cn/"
  },
  {
    "id": "llitmuy8u",
    "cn": "神明神社本殿",
    "name": "神明神社本殿",
    "image": "https://image.xinu.ink/pic/data/873/images/llitmuy8u-1720255739052.jpg",
    "ep": 12,
    "s": 1105,
    "geo": [
      35.539,
      139.6873
    ]
  },
  {
    "id": "n6z8foige",
    "name": "神明神社 本殿前",
    "image": "https://image.xinu.ink/pic/data/873/images/n6z8foige_1723575658948.jpg",
    "ep": 12,
    "s": 1120,
    "geo": [
      35.539,
      139.6872
    ],
    "origin": "Anitabi@Lilin",
    "originURL": "https://anitabi.cn/"
  },
  {
    "id": "n6z0tvham",
    "name": "神明神社",
    "image": "https://image.xinu.ink/pic/data/873/images/n6z0tvham_1723575267079.jpg",
    "ep": 12,
    "s": 1125,
    "geo": [
      35.5389,
      139.6872
    ],
    "origin": "Anitabi@Lilin",
    "originURL": "https://anitabi.cn/"
  },
  {
    "id": "n6z99l2h8",
    "name": "神明神社 本殿",
    "image": "https://image.xinu.ink/pic/data/873/images/n6z99l2h8_1723575707172.jpg",
    "ep": 12,
    "s": 1203,
    "geo": [
      35.539,
      139.6873
    ],
    "origin": "Anitabi@Lilin",
    "originURL": "https://anitabi.cn/"
  },
  {
    "id": "pd8vr75rv",
    "name": "HILL VALLEY",
    "image": "https://image.xinu.ink/pic/data/873/images/pd8vr75rv_1729709055916.jpg",
    "ep": 13,
    "s": 397,
    "geo": [
      35.5281,
      139.6977
    ],
    "origin": "Anitabi@Lilin",
    "originURL": "https://anitabi.cn/"
  },
  {
    "id": "n4k0f73ng",
    "name": "ラ チッタデッラ中央噴水広場",
    "image": "https://image.xinu.ink/pic/data/873/images/n4k0f73ng-1723385839331.jpg",
    "ep": 13,
    "s": 523,
    "geo": [
      35.5284,
      139.6978
    ],
    "origin": "Anitabi@Lilin",
    "originURL": "https://anitabi.cn/"
  },
  {
    "id": "n6zatf36o",
    "name": "神明神社 本殿前階段",
    "image": "https://image.xinu.ink/pic/data/873/images/n6zatf36o_1723575802607.jpg",
    "ep": 13,
    "s": 737,
    "geo": [
      35.539,
      139.6872
    ],
    "origin": "Anitabi@Lilin",
    "originURL": "https://anitabi.cn/"
  },
  {
    "id": "lznves3dk",
    "cn": "公交站 スタルヒン球場前站",
    "name": "バス停　スタルヒン球場前駅",
    "image": "https://image.xinu.ink/pic/data/873/images/lznves3dk-1720181273234.jpg",
    "ep": 13,
    "s": 1265,
    "geo": [
      43.7897,
      142.3671
    ],
    "origin": "Anitabi@うに",
    "originURL": "https://anitabi.cn/"
  },
  {
    "id": "ntvxjs39d",
    "cn": "东京羽田机场05号跑道",
    "name": "羽田空港05番滑走路",
    "image": "https://image.xinu.ink/pic/data/873/images/ntvxjs39d_1726423937997.jpg",
    "ep": "MV1",
    "s": 14,
    "geo": [
      35.5345,
      139.8151
    ]
  },
  {
    "id": "n4l816atm",
    "name": "浮島町公園",
    "image": "https://image.xinu.ink/pic/data/873/images/n4l816atm-1723388468413.jpg",
    "ep": "MV1",
    "s": 48,
    "geo": [
      35.5218,
      139.7889
    ],
    "origin": "@ねぎ太",
    "originLink": "https://negitap.hateblo.jp/entry/2023/11/24/214524"
  },
  {
    "id": "n6wzekk8s",
    "name": "大島3丁目交差点",
    "image": "https://image.xinu.ink/pic/data/873/images/n6wzekk8s_1723570792383.jpg",
    "ep": "MV1",
    "s": 54,
    "geo": [
      35.5195,
      139.7163
    ],
    "origin": "@ねぎ太",
    "originLink": "https://negitap.hateblo.jp/entry/2023/11/24/214524"
  },
  {
    "id": "pd9hw6y0b",
    "cn": "川崎市民广场",
    "name": "川崎市民広場",
    "image": "https://image.xinu.ink/pic/data/873/images/pd9hw6y0b_1729710395737.jpg",
    "ep": "MV1",
    "s": 64,
    "geo": [
      35.5268,
      139.7117
    ],
    "origin": "@ねぎ太",
    "originLink": "https://negitap.hateblo.jp/entry/2023/11/24/214524"
  },
  {
    "id": "pd8ti1a81",
    "cn": "川崎HelloBridge",
    "name": "川崎ハローブリッジ",
    "image": "https://image.xinu.ink/pic/data/873/images/pd8ti1a81_1729708921890.jpg",
    "ep": "MV1",
    "s": 70,
    "geo": [
      35.5297,
      139.7046
    ],
    "origin": "@ねぎ太",
    "originLink": "https://negitap.hateblo.jp/entry/2023/11/24/214524"
  },
  {
    "id": "n4j0jcnqy",
    "cn": "川崎HelloBridge 楼梯",
    "name": "川崎ハローブリッジ 階段",
    "image": "https://image.xinu.ink/pic/data/873/images/n4j0jcnqy-1723383648668.jpg",
    "ep": "MV1",
    "s": 80,
    "geo": [
      35.53,
      139.7043
    ],
    "origin": "@ねぎ太",
    "originLink": "https://negitap.hateblo.jp/entry/2023/11/24/214524"
  },
  {
    "id": "n6l4vug0l",
    "name": "JR川崎駅改札前時計台",
    "image": "https://image.xinu.ink/pic/data/873/images/n6l4vug0l_1723544969291.jpg",
    "ep": "MV1",
    "s": 145,
    "geo": [
      35.5314,
      139.697
    ],
    "origin": "Anitabi@Lilin",
    "originURL": "https://anitabi.cn/"
  },
  {
    "id": "n4jvgtp0u",
    "name": "四季の道",
    "image": "https://image.xinu.ink/pic/data/873/images/n4jvgtp0u-1723385595067.jpg",
    "ep": "MV1",
    "s": 151,
    "geo": [
      35.5341,
      139.6957
    ],
    "origin": "Anitabi@Lilin",
    "originURL": "https://anitabi.cn/"
  },
  {
    "id": "n9475ox4u",
    "name": "川崎マリエン展望室",
    "image": "https://image.xinu.ink/pic/data/873/images/n9475ox4u_1723743220889.jpg",
    "ep": "MV5",
    "s": 5,
    "geo": [
      35.4964,
      139.7631
    ],
    "origin": "@kobaya",
    "originLink": "https://www.google.com/maps/d/u/0/edit?mid=1MHZGV3AafVleHD6pVEo5qp_sUZYI9l8&usp=sharing"
  },
  {
    "id": "n4lc01u52",
    "name": "東亜石油 京浜製油所",
    "image": "https://image.xinu.ink/pic/data/873/images/n4lc01u52-1723388824931.jpg",
    "ep": "MV5",
    "s": 6,
    "geo": [
      35.512,
      139.739
    ],
    "origin": "@ねぎ太",
    "originLink": "https://negitap.hateblo.jp/entry/2023/11/24/214524"
  },
  {
    "id": "pd9gc2r5j",
    "name": "チネチッタ通り",
    "image": "https://image.xinu.ink/pic/data/873/images/pd9gc2r5j_1729710302873.jpg",
    "ep": "MV5",
    "s": 7,
    "geo": [
      35.5283,
      139.6975
    ],
    "origin": "Anitabi@Lilin",
    "originURL": "https://anitabi.cn/"
  },
  {
    "id": "n4kzg33d5",
    "name": "大師橋",
    "image": "https://image.xinu.ink/pic/data/873/images/n4kzg33d5-1723387924666.jpg",
    "ep": "MV5",
    "s": 11,
    "geo": [
      35.5439,
      139.7413
    ],
    "origin": "@ねぎ太",
    "originLink": "https://negitap.hateblo.jp/entry/2023/11/24/214524"
  },
  {
    "id": "n6zpa0txs",
    "name": "味の素樋管 第2排水口",
    "image": "https://image.xinu.ink/pic/data/873/images/n6zpa0txs_1723576756236.jpg",
    "ep": "MV5",
    "s": 20,
    "geo": [
      35.5382,
      139.7197
    ],
    "origin": "@ねぎ太",
    "originLink": "https://negitap.hateblo.jp/entry/2023/11/24/214524"
  },
  {
    "id": "n6dc5xmqr",
    "name": "ミューザ川崎 シンフォニーホール前交差点",
    "image": "https://image.xinu.ink/pic/data/873/images/n6dc5xmqr_1723527990070.jpg",
    "ep": "MV5",
    "s": 22,
    "geo": [
      35.5315,
      139.6939
    ],
    "origin": "@ねぎ太",
    "originLink": "https://negitap.hateblo.jp/entry/2023/11/24/214524"
  },
  {
    "id": "n4lflwvjt",
    "name": "川崎コンビナート 千鳥町ヤード",
    "image": "https://image.xinu.ink/pic/data/873/images/n4lflwvjt-1723389034397.jpg",
    "ep": "MV5",
    "s": 36,
    "geo": [
      35.5186,
      139.7507
    ],
    "origin": "@ねぎ太",
    "originLink": "https://negitap.hateblo.jp/entry/2023/11/24/214524"
  },
  {
    "id": "ndellxy1g",
    "name": "ミューザ川崎 シンフォニーホール",
    "image": "https://image.xinu.ink/pic/data/873/images/ndellxy1g_1724079289550.jpg",
    "ep": "MV5",
    "s": 43,
    "geo": [
      35.531,
      139.6947
    ],
    "origin": "@ねぎ太",
    "originLink": "https://negitap.hateblo.jp/entry/2023/11/24/214524"
  },
  {
    "id": "n6wsuwqfk",
    "cn": "7-Eleven 川崎站前南店",
    "name": "セブン-イレブン 川崎駅前南店",
    "image": "https://image.xinu.ink/pic/data/873/images/n6wsuwqfk_1723570370753.jpg",
    "ep": "MV5",
    "s": 91,
    "geo": [
      35.5296,
      139.6977
    ],
    "origin": "@ねぎ太",
    "originLink": "https://negitap.hateblo.jp/entry/2023/11/24/214524"
  },
  {
    "id": "n4jcsygc7",
    "name": "アゼリア地下街27番出口",
    "image": "https://image.xinu.ink/pic/data/873/images/n4jcsygc7-1723384359171.jpg",
    "ep": "MV5",
    "s": 93,
    "geo": [
      35.5303,
      139.6988
    ],
    "origin": "@ねぎ太",
    "originLink": "https://negitap.hateblo.jp/entry/2023/11/24/214524"
  },
  {
    "id": "pdahfn627",
    "name": "東扇島東公園 みさき広場",
    "image": "https://image.xinu.ink/pic/data/873/images/pdahfn627_1729712551536.jpg",
    "ep": "MV5",
    "s": 213,
    "geo": [
      35.5047,
      139.7776
    ],
    "origin": "@ねぎ太",
    "originLink": "https://negitap.hateblo.jp/entry/2023/11/24/214524"
  },
  {
    "id": "ob4u0e433",
    "name": "川崎駅前南交差点",
    "image": "https://image.xinu.ink/pic/data/873/images/ob4u0e433_1726722624435.jpg",
    "ep": "宣传图/版权绘/封面",
    "geo": [
      35.5295,
      139.6979
    ],
    "origin": "Anitabi@AmaiAya",
    "originURL": "https://anitabi.cn/"
  },
  {
    "id": "ob4mpmk02",
    "name": "川崎モアーズ プチカレーター",
    "image": "https://image.xinu.ink/pic/data/873/images/ob4mpmk02_1726722970500.jpg",
    "ep": "宣传图/版权绘/封面",
    "geo": [
      35.5309,
      139.6994
    ],
    "origin": "Anitabi@AmaiAya",
    "originURL": "https://anitabi.cn/"
  },
  {
    "id": "ob5av1j6c",
    "name": "東扇島東公園",
    "image": "https://image.xinu.ink/pic/data/873/images/ob5av1j6c_1726723526298.jpg",
    "ep": "宣传图/版权绘/封面",
    "geo": [
      35.5056,
      139.773
    ],
    "origin": "Anitabi@AmaiAya",
    "originURL": "https://anitabi.cn/"
  },
  {
    "id": "o50a2sswz",
    "name": "ラ チッタデッラ",
    "image": "https://image.xinu.ink/pic/data/873/images/o50a2sswz_1726242408557.jpg",
    "ep": "宣传图/版权绘/封面",
    "geo": [
      35.5283,
      139.6979
    ],
    "origin": "Anitabi@AmaiAya",
    "originURL": "https://anitabi.cn/"
  },
  {
    "id": "t9ue986dr",
    "name": "九江路十字路口",
    "image": "https://image.xinu.ink/pic/data/873/images/t9ue986dr-1740726883196.jpg",
    "ep": "宣传图/版权绘/封面",
    "geo": [
      31.2394,
      121.4837
    ],
    "origin": "Anitabi@Azusa",
    "originURL": "https://anitabi.cn/"
  },
  {
    "id": "ujat9v608",
    "cn": "MUZA川崎交响乐大厅",
    "name": "ミューザ川崎シンフォニーホール",
    "image": "https://image.xinu.ink/pic/data/873/images/ujat9v608-1744289088331.jpg",
    "ep": 13,
    "s": 1272,
    "geo": [
      35.5309,
      139.6945
    ],
    "origin": "Anitabi@Niamos!",
    "originURL": "https://anitabi.cn/"
  },
  {
    "id": "ukafzbvq5",
    "cn": "奥林匹克公园中心区（东门）",
    "name": "国家体育场 鸟巢",
    "image": "https://image.xinu.ink/pic/data/873/images/ukafzbvq5-1744366593138.jpg",
    "ep": "宣传图/版权绘/封面",
    "geo": [
      39.9932,
      116.3925
    ],
    "origin": "Anitabi@qingwan",
    "originURL": "https://anitabi.cn/"
  },
  {
    "id": "2d0krts",
    "cn": "东京站 丸之内站前广场",
    "name": "東京駅 丸の内駅前広場",
    "image": "https://image.xinu.ink/pic/data/873/images/2d0krts_1752150957865.jpg",
    "ep": "剧场版总集篇前篇",
    "s": "",
    "geo": [
      35.6816,
      139.7654
    ],
    "origin": "Anitabi@Lilin",
    "originURL": "https://anitabi.cn/"
  },
  {
    "id": "3cq2tt1",
    "cn": "新干线车内",
    "name": "新幹線車内",
    "image": "https://image.xinu.ink/pic/data/873/images/3cq2tt1_1754310098129.jpg",
    "ep": 1,
    "s": 23,
    "geo": [
      35.6826,
      139.7689
    ],
    "origin": "Anitabi@Lilin",
    "originURL": "https://anitabi.cn/"
  },
  {
    "id": "3cq7dgf",
    "name": "武道館",
    "image": "https://image.xinu.ink/pic/data/873/images/3cq7dgf_1754310310778.jpg",
    "ep": "OP",
    "s": 188,
    "geo": [
      35.6933,
      139.7498
    ],
    "origin": "Anitabi@Lilin",
    "originURL": "https://anitabi.cn/"
  },
  {
    "id": "3cql1aw",
    "name": "ラゾーナ川崎プラザ 2階入口",
    "image": "https://image.xinu.ink/pic/data/873/images/3cql1aw_1754310946977.jpg",
    "ep": 1,
    "s": 1256,
    "geo": [
      35.532,
      139.6962
    ],
    "origin": "Anitabi@Lilin",
    "originURL": "https://anitabi.cn/"
  },
  {
    "id": "5i9we90",
    "name": "川崎銀柳街",
    "image": "https://image.xinu.ink/pic/data/873/images/5i9we90_1758999285180.jpg",
    "ep": 1,
    "s": 595,
    "geo": [
      35.5297,
      139.6996
    ],
    "origin": "Anitabi@Lilin",
    "originURL": "https://anitabi.cn/"
  },
  {
    "id": "5iaivxd",
    "name": "川崎市幸区戸手本町2-381-1",
    "image": "https://image.xinu.ink/pic/data/873/images/5iaivxd_1759000336069.jpg",
    "ep": 1,
    "s": 1237,
    "geo": [
      35.5392,
      139.6863
    ],
    "origin": "Anitabi@Lilin",
    "originURL": "https://anitabi.cn/"
  },
  {
    "id": "4kd28w9",
    "cn": "川崎市幸区神明町",
    "name": "川崎市幸区神明町",
    "image": "https://image.xinu.ink/pic/data/873/images/4kd28w9-1756948757318.jpg",
    "ep": "剧场版总集篇前篇",
    "geo": [
      35.5376,
      139.6874
    ],
    "origin": "@2outni4",
    "originLink": "https://x.com/2outni4/status/1963209030412714083"
  },
  {
    "id": "5ia6r50",
    "name": "京急川崎駅前",
    "image": "https://image.xinu.ink/pic/data/873/images/5ia6r50_1758999782416.jpg",
    "ep": "剧场版总集篇前篇",
    "geo": [
      35.5318,
      139.6997
    ],
    "origin": "Anitabi@Lilin",
    "originURL": "https://anitabi.cn/"
  },
  {
    "id": "4untpts",
    "name": "前海欢乐港湾摩天轮",
    "image": "https://image.xinu.ink/pic/data/873/images/4untpts-1757571523101.jpg",
    "ep": "宣传图/版权绘/封面",
    "geo": [
      22.5446,
      113.8828
    ],
    "origin": "Anitabi@月即别",
    "originURL": "https://anitabi.cn/"
  },
  {
    "id": "4uo3emp",
    "name": "世界之窗 悉尼铁桥",
    "image": "https://image.xinu.ink/pic/data/873/images/4uo3emp-1757571963812.jpg",
    "ep": "宣传图/版权绘/封面",
    "geo": [
      22.5343,
      113.9705
    ],
    "origin": "Anitabi@月即别",
    "originURL": "https://anitabi.cn/"
  },
  {
    "id": "4uoeke1",
    "name": "南头古城 牌坊",
    "image": "https://image.xinu.ink/pic/data/873/images/4uoeke1-1757572484220.jpg",
    "ep": "宣传图/版权绘/封面",
    "geo": [
      22.5437,
      113.9157
    ],
    "origin": "Anitabi@月即别",
    "originURL": "https://anitabi.cn/"
  },
  {
    "id": "4uohoo4",
    "name": "背仔角灯塔",
    "image": "https://image.xinu.ink/pic/data/873/images/4uohoo4-1757572625786.jpg",
    "ep": "宣传图/版权绘/封面",
    "geo": [
      22.5941,
      114.3357
    ],
    "origin": "Anitabi@月即别",
    "originURL": "https://anitabi.cn/"
  },
  {
    "id": "5tl06kv",
    "cn": "Mos Burger 涩谷道玄坂店",
    "name": "モスバーガー渋谷道玄坂店",
    "image": "https://image.xinu.ink/pic/data/873/images/5tl06kv_1759683067931.jpg",
    "ep": 3,
    "s": 597,
    "geo": [
      35.6592,
      139.6979
    ],
    "origin": "Anitabi@Lilin",
    "originURL": "https://anitabi.cn/"
  },
  {
    "id": "5p342qc",
    "name": "カードボックス青馬堂 矢向店",
    "image": "https://image.xinu.ink/pic/data/873/images/5p342qc_1759411148295.jpg",
    "ep": "剧场版总集篇后篇",
    "geo": [
      35.5379,
      139.6828
    ],
    "origin": "Anitabi@Lilin",
    "originURL": "https://anitabi.cn/"
  },
  {
    "id": "5q0qxr4",
    "name": "Solo殿町北",
    "image": "https://image.xinu.ink/pic/data/873/images/5q0qxr4-1759467684608.jpg",
    "ep": "宣传图/版权绘/封面",
    "geo": [
      35.5406,
      139.7484
    ]
  },
  {
    "id": "5t0v88y",
    "name": "Zepp DiverCity TOKYO",
    "image": "https://image.xinu.ink/pic/data/873/images/5t0v88y_1759649240604.jpg",
    "ep": "宣传图/版权绘/封面",
    "geo": [
      35.6247,
      139.7746
    ],
    "origin": "Anitabi@Lilin",
    "originURL": "https://anitabi.cn/"
  },
  {
    "id": "6u4usb1",
    "name": "中国华润大厦（春笋），深圳湾",
    "image": "https://image.xinu.ink/pic/data/873/images/6u4usb1-1761893257581.jpg",
    "ep": "宣传图/版权绘/封面",
    "geo": [
      22.5132,
      113.9464
    ],
    "origin": "Anitabi@月即别",
    "originURL": "https://anitabi.cn/"
  },
  {
    "id": "6gdlay9",
    "cn": "下鸭神社",
    "name": "下鴨神社",
    "image": "https://image.xinu.ink/pic/data/873/images/6gdlay9-1761061377628.jpg",
    "ep": null,
    "geo": [
      35.0381,
      135.7728
    ],
    "origin": "Anitabi@澄蔦",
    "originURL": "https://anitabi.cn/"
  }
]