[
  {
    "id": "n7tkm4yhy",
    "cn": "多佛尔城堡",
    "name": "Dover Castle",
    "image": "https://image.xinu.ink/pic/data/748/images/n7tkm4yhy-1723641813963.jpg",
    "ep": "",
    "geo": [
      51.1284,
      1.3228
    ],
    "origin": "Anitabi@Zyglisfer",
    "originURL": "https://anitabi.cn/"
  },
  {
    "id": "n7tqe8eui",
    "name": "Drop Redoubt Fort",
    "image": "https://image.xinu.ink/pic/data/748/images/n7tqe8eui-1723642040677.jpg",
    "ep": "",
    "geo": [
      51.1227,
      1.3076
    ],
    "origin": "Anitabi@Zyglisfer",
    "originURL": "https://anitabi.cn/"
  }
]